Workbook
Name aporte: Planilha1!$C$21:$C$21
Name patrimonio: Planilha1!$C$24:$C$24
Name qtd_anos: Planilha1!$C$22:$C$22
Name rendimento_carteira: Planilha1!$C$16:$C$16
Name sugestao_investimento: Planilha1!$C$17:$C$17
Name taxa_mensal: Planilha1!$C$23:$C$23

Sheet Planilha1
B12: PREENCHA SOMENTE AS CÉLULAS AMARELAS
B14: CONFIGURAÇÕES
B15: Salário | C15: 10000
B16: Taxa de Rendimento Carteira | C16: 0.02
B17: Sugestão de Investimento - (30% do Salário) | C17: =C15*30% -> 3000
B20: INVESTIMENTO MENSAL
B21: Quanto investir por mês? | C21: 500
B22: Por Quantos anos? | C22: 5
B23: Taxa de RendimentO mensal? | C23: 0.01079
B24: Patrimônio Acumulado? | C24: {=FV(taxa_mensal,qtd_anos*12,aporte*-1)} -> 41888.457
B25: Dividendos Mensais? | C25: {=patrimonio*rendimento_carteira} -> 837.76914
B28: CENÁRIOS | D28: Div. Mensais
B29: Valor em 2 anos ? | C29: =FV($C$23,$A30*12,$C$21*-1) -> 13613.814 | D29: {=C29*rendimento_carteira} -> 272.27627
A30: 2 | B30: Valor em 5 anos ? | C30: =FV($C$23,$A31*12,$C$21*-1) -> 41888.457 | D30: {=C30*rendimento_carteira} -> 837.76914
A31: 5 | B31: Valor em 10 anos ? | C31: =FV($C$23,$A32*12,$C$21*-1) -> 121642.11 | D31: {=C31*rendimento_carteira} -> 2432.8421
A32: 10 | B32: Valor em 20 anos ? | C32: =FV($C$23,$A33*12,$C$21*-1) -> 562599.2 | D32: {=C32*rendimento_carteira} -> 11251.984
A33: 20 | B33: Valor em 30 anos ? | C33: =FV($C$23,$A34*12,$C$21*-1) -> 2161084.8 | D33: {=C33*rendimento_carteira} -> 43221.697
A34: 30
B36: DEFINA SEU PERFIL DE INVESTIDOR | C36: Agressivo
B37: VALOR MENSAL INVESTIDO | C37: =C21 -> 500
B40: EM QUAIS SEGMENTOS VOCÊ DEVERIA APORTAR
B41: TIPO DE FII | C41: PERCENTUAL SUGERIDO | D41: VALORES
B42: PAPEL | C42: =VLOOKUP($C$36&"_"&B42,'Ref.Investidores'!$A:$D,4,FALSE) -> 0.4 | D42: =$C$37*C42 -> 200
B43: TIJOLO | C43: =VLOOKUP($C$36&"_"&B43,'Ref.Investidores'!$A:$D,4,FALSE) -> 0.2 | D43: =$C$37*C43 -> 100
B44: HIBRIDOS | C44: =VLOOKUP($C$36&"_"&B44,'Ref.Investidores'!$A:$D,4,FALSE) -> 0.05 | D44: =$C$37*C44 -> 25
B45: FOFS | C45: =VLOOKUP($C$36&"_"&B45,'Ref.Investidores'!$A:$D,4,FALSE) -> 0.05 | D45: =$C$37*C45 -> 25
B46: DESENVOLVIMENTO | C46: =VLOOKUP($C$36&"_"&B46,'Ref.Investidores'!$A:$D,4,FALSE) -> 0.05 | D46: =$C$37*C46 -> 25
B47: HOTELARIA | C47: =VLOOKUP($C$36&"_"&B47,'Ref.Investidores'!$A:$D,4,FALSE) -> 0.05 | D47: =$C$37*C47 -> 25
B48: LOGISTICA | C48: =VLOOKUP($C$36&"_"&B48,'Ref.Investidores'!$A:$D,4,FALSE) -> 0.2 | D48: =$C$37*C48 -> 100
B49: TOTAL | C49: =SUM(C42:C48) -> 1 | D49: =SUM(D42:D48) -> 500

Sheet Ref.Investidores
A3: CHAVE | B3: PERFIL | C3: TIPO DE FII | D3: %
A4: =B4&"_"&C4 -> Conservador_PAPEL | B4: Conservador | C4: PAPEL | D4: 0.2
A5: =B5&"_"&C5 -> Conservador_TIJOLO | B5: Conservador | C5: TIJOLO | D5: 0.4
A6: =B6&"_"&C6 -> Conservador_HIBRIDOS | B6: Conservador | C6: HIBRIDOS | D6: 0.1
A7: =B7&"_"&C7 -> Conservador_FOFS | B7: Conservador | C7: FOFS | D7: 0.1
A8: =B8&"_"&C8 -> Conservador_DESENVOLVIMENTO | B8: Conservador | C8: DESENVOLVIMENTO | D8: 0
A9: =B9&"_"&C9 -> Conservador_HOTELARIA | B9: Conservador | C9: HOTELARIA | D9: 0
A10: =B10&"_"&C10 -> Conservador_LOGISTICA | B10: Conservador | C10: LOGISTICA | D10: 0.2
A11: =B11&"_"&C11 -> Moderado_PAPEL | B11: Moderado | C11: PAPEL | D11: 0.3
A12: =B12&"_"&C12 -> Moderado_TIJOLO | B12: Moderado | C12: TIJOLO | D12: 0.3
A13: =B13&"_"&C13 -> Moderado_HIBRIDOS | B13: Moderado | C13: HIBRIDOS | D13: 0.1
A14: =B14&"_"&C14 -> Moderado_FOFS | B14: Moderado | C14: FOFS | D14: 0.1
A15: =B15&"_"&C15 -> Moderado_DESENVOLVIMENTO | B15: Moderado | C15: DESENVOLVIMENTO | D15: 0.05
... A24: =B24&"_"&C24 -> Agressivo_LOGISTICA | B24: Agressivo | C24: LOGISTICA | D24: 0.2
